s3stash/__init__.py
s3stash/stash.py
s3stash/util.py
s3stash-1.2.1.dist-info/DESCRIPTION.rst
s3stash-1.2.1.dist-info/METADATA
s3stash-1.2.1.dist-info/RECORD
s3stash-1.2.1.dist-info/WHEEL
s3stash-1.2.1.dist-info/metadata.json
s3stash-1.2.1.dist-info/top_level.txt
