Metadata-Version: 2.0
Name: s3stash
Version: 1.2.1
Summary: Very simple module that uses boto3 to stash a file in S3
Home-page: https://github.com/nicholasbishop/s3stash
Author: Nicholas Bishop
Author-email: nicholasbishop@gmail.com
License: Apache 2.0
Platform: UNKNOWN
Requires-Dist: boto3 (>=1.4.0)
